locust_influxdb_listener/__init__.py
locust_influxdb_listener-1.0.2.dist-info/LICENSE
locust_influxdb_listener-1.0.2.dist-info/METADATA
locust_influxdb_listener-1.0.2.dist-info/WHEEL
locust_influxdb_listener-1.0.2.dist-info/top_level.txt
locust_influxdb_listener-1.0.2.dist-info/RECORD
