Metadata-Version: 2.1
Name: locust-influxdb-listener
Version: 1.0.2
Summary: Locust.io 1.X influxdb listener
Home-page: https://github.com/pjcalvo/locust-influxdb-listener
Author: Pablo Calvo
Author-email: pjcalvov@gmail.com
Classifier: Programming Language :: Python :: 3
Classifier: License :: OSI Approved :: MIT License
Classifier: Operating System :: OS Independent
Requires-Python: >=3.6
License-File: LICENSE
Requires-Dist: locust >=1.5.0
Requires-Dist: influxdb >=5.2.2
